spinmob/__init__.py
spinmob/_data.py
spinmob/_dialogs.py
spinmob/_functions.py
spinmob/_plot.py
spinmob/_plot_complex.py
spinmob/_plot_image.py
spinmob/_plot_magphase.py
spinmob/_plot_parametric.py
spinmob/_plot_realimag.py
spinmob/_plot_xy.py
spinmob/_plotting.py
spinmob/_plotting_mess.py
spinmob/_prefs.py
spinmob/_pylab_colormap.py
spinmob/_pylab_tweaks.py
spinmob/_settings.py
spinmob/_spline.py
spinmob/_theme_fusion_dark.py
spinmob/_thread.py
spinmob/setup.py
spinmob/egg/__init__.py
spinmob/egg/_gui.py
spinmob/egg/_syntax.py
spinmob/egg/example_daq.py
spinmob/egg/example_from_wiki.py
spinmob/egg/example_from_wiki_2.py
spinmob/egg/example_other_widgets.py
spinmob/egg/example_really_basic.py
spinmob/egg/example_sliders.py
spinmob/egg/example_sweeper.py
spinmob/egg/DataboxProcessor/histogram_plot_script.py
spinmob/tests/__init__.py
spinmob/tests/spinmob_tests.py
spinmob/tests/test__databox.py
spinmob/tests/test__dialogs.py
spinmob/tests/test__egg.py
spinmob/tests/test__fitter.py
spinmob/tests/test__functions.py
spinmob/tests/test__plot.py
spinmob/tests/fixtures/basic.dat
spinmob/tests/fixtures/basic2.dat
spinmob/tests/fixtures/basic3.dat
spinmob/tests/fixtures/comma.dat
spinmob/tests/fixtures/difficult.binary
spinmob/tests/fixtures/fit.csv
spinmob/tests/fixtures/float16.binary
spinmob/tests/fixtures/headers.dat
spinmob/tests/fixtures/mixed_complex.dat
spinmob/tests/fixtures/one_column.dat
spinmob/tests/fixtures/one_row.dat
spinmob/tests/fixtures/semicolon.dat
spinmob-3.13.7.dist-info/licenses/LICENSE.txt
spinmob-3.13.7.dist-info/METADATA
spinmob-3.13.7.dist-info/WHEEL
spinmob-3.13.7.dist-info/top_level.txt
spinmob-3.13.7.dist-info/RECORD
