Metadata-Version: 2.4
Name: spinmob
Version: 3.13.7
Summary: Data handling, plotting, analysis, and GUI building for scientific labs
Home-page: https://github.com/Spinmob/spinmob
Author: Jack Sankey
Author-email: jack.sankey@gmail.com
License-File: LICENSE.txt
Requires-Dist: scipy
Requires-Dist: matplotlib
Requires-Dist: lmfit
Requires-Dist: pyopengl
Requires-Dist: pyqtgraph~=0.14.0
Dynamic: author
Dynamic: author-email
Dynamic: home-page
Dynamic: license-file
Dynamic: requires-dist
Dynamic: summary
